aiobearychat/__init__.py
aiobearychat/abc.py
aiobearychat/sansio.py
aiobearychat/openapi/__init__.py
aiobearychat/openapi/aiohttp.py
aiobearychat/openapi/channel_api.py
aiobearychat/openapi/core.py
aiobearychat/openapi/emoji_api.py
aiobearychat/openapi/message_api.py
aiobearychat/openapi/meta_api.py
aiobearychat/openapi/p2p_api.py
aiobearychat/openapi/rtm_api.py
aiobearychat/openapi/session_channel_api.py
aiobearychat/openapi/sticker_api.py
aiobearychat/openapi/team_api.py
aiobearychat/openapi/user_api.py
aiobearychat/openapi/vchannel_api.py
aiobearychat/requesters/__init__.py
aiobearychat/requesters/aiohttp.py
aiobearychat/rtm/__init__.py
aiobearychat/rtm/aiohttp.py
aiobearychat/rtm/http.py
aiobearychat-0.2.0.dist-info/DESCRIPTION.rst
aiobearychat-0.2.0.dist-info/METADATA
aiobearychat-0.2.0.dist-info/RECORD
aiobearychat-0.2.0.dist-info/WHEEL
aiobearychat-0.2.0.dist-info/metadata.json
aiobearychat-0.2.0.dist-info/top_level.txt
