Metadata-Version: 2.0
Name: aiobearychat
Version: 0.2.0
Summary: BearyChat 异步 Python SDK
Home-page: https://github.com/mozillazg/aiobearychat
Author: mozillazg
Author-email: mozillazg101@gmail.com
License: MIT
Keywords: aiobearychat
Platform: UNKNOWN
Classifier: Development Status :: 5 - Production/Stable
Classifier: Intended Audience :: Developers
Classifier: License :: OSI Approved :: MIT License
Classifier: Programming Language :: Python :: 3
Classifier: Programming Language :: Python :: 3.5
Classifier: Programming Language :: Python :: 3.6
Classifier: Programming Language :: Python :: Implementation :: CPython
Requires-Dist: attrs
Requires-Dist: attrs
Provides-Extra: aiohttp
Requires-Dist: aiohttp; extra == 'aiohttp'
